faker_airtravel/__init__.py
faker_airtravel/airports.py
faker_airtravel/constants.py
faker_airtravel/tests/test_airports.py
faker_airtravel/tests/test_origin_detination.py
faker_airtravel-0.4.dist-info/LICENSE
faker_airtravel-0.4.dist-info/WHEEL
faker_airtravel-0.4.dist-info/METADATA
faker_airtravel-0.4.dist-info/RECORD
