Metadata-Version: 2.1
Name: faker_airtravel
Version: 0.4
Summary: AirTravel Faker Community Provider
Home-page: https://github.com/dkotschessa/faker_airtravel.git
Author: David Kotschessa
Author-email: itzdavey@gmail.com
Classifier: License :: OSI Approved :: MIT License
Requires-Dist: pytest ; extra == "test"
Requires-Dist: pytest-cov ; extra == "test"
Requires-Dist: tox ; extra == "test"
Provides-Extra: test
